setup.cfg
setup.py
dokcer/__init__.py
dokcer/cli.py
dokcer.egg-info/PKG-INFO
dokcer.egg-info/SOURCES.txt
dokcer.egg-info/dependency_links.txt
dokcer.egg-info/entry_points.txt
dokcer.egg-info/requires.txt
dokcer.egg-info/top_level.txt
dokcer/lib/__init__.py
dokcer/lib/docker_client.py
dokcer/lib/Docker/__init__.py
dokcer/lib/Docker/Container/__init__.py
dokcer/lib/Docker/Container/command.py
dokcer/lib/Docker/Container/cp.py
dokcer/lib/Docker/Container/create.py
dokcer/lib/Docker/Container/exec.py
dokcer/lib/Docker/Container/exec_create.py
dokcer/lib/Docker/Container/exec_start.py
dokcer/lib/Docker/Container/inspect.py
dokcer/lib/Docker/Container/list.py
dokcer/lib/Docker/Container/logs.py
dokcer/lib/Docker/Container/ls.py
dokcer/lib/Docker/Container/ps.py
dokcer/lib/Docker/Container/rename.py
dokcer/lib/Docker/Container/restart.py
dokcer/lib/Docker/Container/rm.py
dokcer/lib/Docker/Container/run.py
dokcer/lib/Docker/Container/start.py
dokcer/lib/Docker/Container/stats.py
dokcer/lib/Docker/Container/top.py
dokcer/lib/Docker/Image/__init__.py
dokcer/lib/Docker/Image/build.py
dokcer/lib/Docker/Image/command.py
dokcer/lib/Docker/Image/history.py
dokcer/lib/Docker/Image/images.py
dokcer/lib/Docker/Image/inspect.py
dokcer/lib/Docker/Image/list.py
dokcer/lib/Docker/Image/ls.py
dokcer/lib/Docker/Image/pull.py
dokcer/lib/Docker/Image/remove.py
dokcer/lib/Docker/Image/rm.py
dokcer/lib/Docker/Image/rmi.py
dokcer/lib/Docker/Image/save.py
dokcer/lib/Docker/Network/__init__.py
dokcer/lib/Docker/Network/command.py
dokcer/lib/Docker/Network/connect.py
dokcer/lib/Docker/Network/create.py
dokcer/lib/Docker/Network/disconnect.py
dokcer/lib/Docker/Network/inspect.py
dokcer/lib/Docker/Network/ls.py
dokcer/lib/Docker/Network/remove.py
dokcer/lib/Docker/Network/rm.py
dokcer/lib/Docker/System/__init__.py
dokcer/lib/Docker/System/command.py
dokcer/lib/Docker/System/info.py
dokcer/lib/Docker/System/inspect.py
dokcer/lib/Docker/System/version.py
dokcer/lib/Docker/Volume/__init__.py
dokcer/lib/Docker/Volume/command.py
dokcer/lib/Docker/Volume/create.py
dokcer/lib/Docker/Volume/inspect.py
dokcer/lib/Docker/Volume/ls.py
dokcer/lib/Docker/Volume/remove.py
