Metadata-Version: 1.1
Name: dokcer
Version: 0.8
Summary: Python based Assistance for Docker
Home-page: https://github.com/qazbnm456/dokcer
Author: Boik Su
Author-email: boik@tdohacker.org
License: UNKNOWN
Download-URL: https://codeload.github.com/qazbnm456/dokcer/tar.gz/0.7
Keywords: 0.8
Platform: UNKNOWN
Classifier: Environment :: Console
Classifier: Intended Audience :: Developers
Classifier: Intended Audience :: System Administrators
Classifier: License :: OSI Approved :: Apache Software License
Classifier: Topic :: Software Development
Classifier: Topic :: Terminals
Classifier: Topic :: Utilities
Classifier: Operating System :: OS Independent
Classifier: Programming Language :: Python
Classifier: Programming Language :: Python :: 2
Classifier: Programming Language :: Python :: 2.6
Classifier: Programming Language :: Python :: 2.7
